datapan-0.1.1.dist-info/METADATA
datapan-0.1.1.dist-info/WHEEL
datapan.cpython-36m-darwin.so
datapan-0.1.1.dist-info/RECORD
