Metadata-Version: 2.1
Name: datapan
Version: 0.1.1
Summary: datapan filters (big) files.
